adjax/__init__.py
adjax/importer.py
adjax/middleware.py
adjax/registry.py
adjax/serializer.py
adjax/urls.py
adjax/views.py
adjax/conf/__init__.py
adjax/conf/settings.py
adjax/static/adjax/base.js
adjax/templates/adjax/interface
adjax/templatetags/__init__.py
adjax/templatetags/adjax.py
adjax/tests/__init__.py
adjax/tests/test_importer.py
adjax/tests/test_middleware.py
adjax/tests/test_registry.py
adjax/tests/test_serializer.py
adjax/tests/test_templatetags.py
adjax/utils/__init__.py
adjax/utils/inspect.py
adjax/utils/types.py
django_adjax-1.0.dist-info/LICENSE
django_adjax-1.0.dist-info/METADATA
django_adjax-1.0.dist-info/WHEEL
django_adjax-1.0.dist-info/top_level.txt
django_adjax-1.0.dist-info/RECORD
